django_status-2.2.1.dist-info/DESCRIPTION.rst
django_status-2.2.1.dist-info/METADATA
django_status-2.2.1.dist-info/RECORD
django_status-2.2.1.dist-info/WHEEL
django_status-2.2.1.dist-info/entry_points.txt
django_status-2.2.1.dist-info/metadata.json
django_status-2.2.1.dist-info/top_level.txt
status/__init__.py
status/__init__.pyc
status/__main__.py
status/apps.py
status/commands.py
status/settings.py
status/urls.py
status/utils.py
status/__pycache__/__init__.cpython-35.pyc
status/__pycache__/apps.cpython-35.pyc
status/__pycache__/settings.cpython-35.pyc
status/__pycache__/urls.cpython-35.pyc
status/__pycache__/utils.cpython-35.pyc
status/api/__init__.py
status/api/mixins.py
status/api/urls.py
status/api/views.py
status/api/__pycache__/__init__.cpython-35.pyc
status/api/__pycache__/mixins.cpython-35.pyc
status/api/__pycache__/urls.cpython-35.pyc
status/api/__pycache__/views.cpython-35.pyc
status/management/__init__.py
status/management/__pycache__/__init__.cpython-35.pyc
status/management/commands/__init__.py
status/management/commands/status.py
status/management/commands/__pycache__/__init__.cpython-35.pyc
status/management/commands/__pycache__/status.cpython-35.pyc
status/providers/__init__.py
status/providers/base.py
status/providers/health.py
status/providers/stats.py
status/providers/__pycache__/__init__.cpython-35.pyc
status/providers/__pycache__/base.cpython-35.pyc
status/providers/__pycache__/health.cpython-35.pyc
status/providers/__pycache__/stats.cpython-35.pyc
status/providers/celery/__init__.py
status/providers/celery/health.py
status/providers/celery/stats.py
status/providers/django/__init__.py
status/providers/django/health.py
status/providers/django/stats.py
status/static/js/health.jsx
status/static/js/main.jsx
status/static/js/stats.jsx
status/static/js/actions/AppActions.js
status/static/js/components/HealthApp.jsx
status/static/js/components/HealthItem.jsx
status/static/js/components/StatsApp.jsx
status/static/js/components/StatsItem.jsx
status/static/js/components/StatsItemKey.jsx
status/static/js/components/StatusApp.jsx
status/static/js/components/StatusItem.jsx
status/static/js/constants/AppConstants.js
status/static/js/dispatcher/AppDispatcher.js
