Metadata-Version: 1.1
Name: django-status
Version: 2.2.1
Summary: Application that provides an API to check the status of some parts and some utilities like ping.
Home-page: https://github.com/PeRDy/django-status
Author: José Antonio Perdiguero López
Author-email: perdy.hh@gmail.com
License: GPLv3
Download-URL: https://github.com/PeRDy/django-status
Keywords: python django database cache celery status check
Platform: UNKNOWN
Classifier: Development Status :: 5 - Production/Stable
Classifier: Framework :: Django
Classifier: Intended Audience :: Developers
Classifier: License :: OSI Approved :: GNU General Public License v3 (GPLv3)
Classifier: Natural Language :: English
Classifier: Programming Language :: Python
Classifier: Programming Language :: Python :: 2
Classifier: Programming Language :: Python :: 3
Classifier: Topic :: Software Development :: Libraries :: Python Modules
